doc_comments_ai/__init__.py
doc_comments_ai/__main__.py
doc_comments_ai/app.py
doc_comments_ai/constants.py
doc_comments_ai/llm.py
doc_comments_ai/treesitter/__init__.py
doc_comments_ai/treesitter/treesitter.py
doc_comments_ai/treesitter/treesitter_c.py
doc_comments_ai/treesitter/treesitter_cpp.py
doc_comments_ai/treesitter/treesitter_cs.py
doc_comments_ai/treesitter/treesitter_go.py
doc_comments_ai/treesitter/treesitter_hs.py
doc_comments_ai/treesitter/treesitter_java.py
doc_comments_ai/treesitter/treesitter_js.py
doc_comments_ai/treesitter/treesitter_kt.py
doc_comments_ai/treesitter/treesitter_py.py
doc_comments_ai/treesitter/treesitter_registry.py
doc_comments_ai/treesitter/treesitter_rs.py
doc_comments_ai/treesitter/treesitter_ts.py
doc_comments_ai/utils.py
doc_comments_ai-0.1.17.dist-info/LICENSE
doc_comments_ai-0.1.17.dist-info/METADATA
doc_comments_ai-0.1.17.dist-info/WHEEL
doc_comments_ai-0.1.17.dist-info/entry_points.txt
doc_comments_ai-0.1.17.dist-info/RECORD
