Metadata-Version: 2.1
Name: doc-comments-ai
Version: 0.1.17
Summary: 
Author: fynnfluegge
Author-email: fynnfluegge@gmx.de
Requires-Python: >=3.9,<4.0
Classifier: Programming Language :: Python :: 3
Classifier: Programming Language :: Python :: 3.9
Classifier: Programming Language :: Python :: 3.10
Classifier: Programming Language :: Python :: 3.11
Classifier: Programming Language :: Python :: 3.12
Requires-Dist: inquirer (>=3.1.3,<4.0.0)
Requires-Dist: langchain (>=0.0.284,<0.0.330)
Requires-Dist: litellm (>=0.1.697,<0.2.0)
Requires-Dist: openai (>=0.27.8,<0.28.0)
Requires-Dist: python-dotenv (>=1.0.0,<2.0.0)
Requires-Dist: tiktoken (>=0.4.0,<0.5.0)
Requires-Dist: tree-sitter (>=0.20.1,<0.21.0)
Requires-Dist: tree-sitter-languages (>=1.7.0,<2.0.0)
Requires-Dist: yaspin (>=3.0.0,<4.0.0)
